lightningrobot_adapter_console/__init__.py
lightningrobot_adapter_console-0.2.2.dist-info/LICENSE
lightningrobot_adapter_console-0.2.2.dist-info/METADATA
lightningrobot_adapter_console-0.2.2.dist-info/WHEEL
lightningrobot_adapter_console-0.2.2.dist-info/RECORD
